spi_em_class/__init__.py
spi_em_class/config.py
spi_em_class/em_compute.py
spi_em_class/em_data.py
spi_em_class/log_writer.py
spi_em_class/pdfreport.py
spi_em_class/symmetry.py
spi_em_class/timer.py
spi_em_class/data/default_config.ini
spi_em_class-0.1.7.data/scripts/spi_em_config.py
spi_em_class-0.1.7.data/scripts/spi_em_create.py
spi_em_class-0.1.7.data/scripts/spi_em_report.py
spi_em_class-0.1.7.data/scripts/spi_em_reset.py
spi_em_class-0.1.7.data/scripts/spi_em_run.py
spi_em_class-0.1.7.data/scripts/spi_em_save.py
spi_em_class-0.1.7.data/scripts/spi_em_save_by_symmetry.py
spi_em_class-0.1.7.dist-info/METADATA
spi_em_class-0.1.7.dist-info/RECORD
spi_em_class-0.1.7.dist-info/WHEEL
spi_em_class-0.1.7.dist-info/top_level.txt
