Metadata-Version: 2.1
Name: spi-em-class
Version: 0.1.7
Summary: Module for EM classification of diffraction images in CXI format.
Home-page: https://gitlab.com/spi_xfel/spi_em_class
Author: Sergey Bobkov
Author-email: s.bobkov@grid.kiae.ru
License: MIT
Platform: UNKNOWN
Requires-Python: >=3.6
Requires-Dist: numba
Requires-Dist: numpy
Requires-Dist: scipy
Requires-Dist: matplotlib
Requires-Dist: h5py
Requires-Dist: tqdm
